catchlib/__init__.py
catchlib/core/__init__.py
catchlib/tests/__init__.py
catchlib/tests/test_0.py
catchlib-1.0.1.dist-info/licenses/LICENSE.txt
catchlib-1.0.1.dist-info/METADATA
catchlib-1.0.1.dist-info/WHEEL
catchlib-1.0.1.dist-info/top_level.txt
catchlib-1.0.1.dist-info/RECORD
