Metadata-Version: 2.4
Name: catchlib
Version: 1.0.1
Summary: This project allows to catch exceptions easily.
Author-email: Johannes <johannes.programming@gmail.com>
License: The MIT License (MIT)
Project-URL: Download, https://pypi.org/project/catchlib/#files
Project-URL: Index, https://pypi.org/project/catchlib/
Project-URL: Source, https://github.com/johannes-programming/catchlib/
Project-URL: Website, https://catchlib.johannes-programming.online/
Classifier: Development Status :: 5 - Production/Stable
Classifier: License :: OSI Approved :: MIT License
Classifier: Natural Language :: English
Classifier: Operating System :: OS Independent
Classifier: Programming Language :: Python
Classifier: Programming Language :: Python :: 3
Classifier: Programming Language :: Python :: 3 :: Only
Classifier: Typing :: Typed
Requires-Python: >=3.11
License-File: LICENSE.txt
Requires-Dist: overloadable<2,>=1.0.9
Dynamic: license-file
